cklass/__init__.py
cklass-0.0.8.dist-info/METADATA
cklass-0.0.8.dist-info/WHEEL
cklass-0.0.8.dist-info/top_level.txt
cklass-0.0.8.dist-info/RECORD
