Metadata-Version: 2.1
Name: cklass
Version: 0.0.8
Summary: Python module for loading config from files and env variables to class
Home-page: https://github.com/arturtamborski/cklass
Author: Artur Tamborski
Author-email: tamborskiartur@gmail.com
License: MIT
Download-URL: https://github.com/arturtamborski/cklass/archive/0.0.8.tar.gz
Keywords: configuration config loader
Platform: UNKNOWN
Classifier: Development Status :: 4 - Beta
Classifier: Topic :: Software Development
Classifier: Intended Audience :: Developers
Classifier: Operating System :: OS Independent
Classifier: Programming Language :: Python :: 2
Classifier: Programming Language :: Python :: 3
Classifier: License :: OSI Approved :: MIT License
